dotbot_firefox.py
dotbot_firefox-1.1.0.dist-info/LICENSE.txt
dotbot_firefox-1.1.0.dist-info/METADATA
dotbot_firefox-1.1.0.dist-info/WHEEL
dotbot_firefox-1.1.0.dist-info/RECORD
