Metadata-Version: 2.1
Name: dotbot-firefox
Version: 1.1.0
Summary: Configure your Firefox profile(s) using dotbot
Home-page: https://github.com/kurtmckee/dotbot-firefox
License: MIT
Keywords: dotbot,dotbot-plugin,firefox,dotfiles
Author: Kurt McKee
Author-email: contactme@kurtmckee.org
Requires-Python: >=3.8
Classifier: License :: OSI Approved :: MIT License
Classifier: Programming Language :: Python :: 3
Classifier: Programming Language :: Python :: 3.8
Classifier: Programming Language :: Python :: 3.9
Classifier: Programming Language :: Python :: 3.10
Classifier: Programming Language :: Python :: 3.11
Requires-Dist: dotbot (>=1.19.0)
Project-URL: Repository, https://github.com/kurtmckee/dotbot-firefox
